parking_eindhoven/__init__.py
parking_eindhoven/exceptions.py
parking_eindhoven/models.py
parking_eindhoven/parking_eindhoven.py
parking_eindhoven/py.typed
parking_eindhoven-2.1.0.dist-info/LICENSE
parking_eindhoven-2.1.0.dist-info/WHEEL
parking_eindhoven-2.1.0.dist-info/METADATA
parking_eindhoven-2.1.0.dist-info/RECORD
