Metadata-Version: 2.1
Name: parking-eindhoven
Version: 2.1.0
Summary: Asynchronous Python client for the parking locations in Eindhoven
Home-page: https://github.com/klaasnicolaas/python-parking-eindhoven
License: MIT
Keywords: parking,eindhoven,locations,api,async,client
Author: Klaas Schoute
Author-email: hello@student-techlife.com
Maintainer: Klaas Schoute
Maintainer-email: hello@student-techlife.com
Requires-Python: >=3.9,<4.0
Classifier: Framework :: AsyncIO
Classifier: Intended Audience :: Developers
Classifier: License :: OSI Approved :: MIT License
Classifier: Natural Language :: English
Classifier: Programming Language :: Python :: 3
Classifier: Programming Language :: Python :: 3.10
Classifier: Programming Language :: Python :: 3.9
Classifier: Topic :: Software Development :: Libraries :: Python Modules
Requires-Dist: aiohttp (>=3.0.0)
Requires-Dist: yarl (>=1.6.0)
Project-URL: Bug Tracker, https://github.com/klaasnicolaas/python-parking-eindhoven/issues
Project-URL: Changelog, https://github.com/klaasnicolaas/python-parking-eindhoven/releases
Project-URL: Documentation, https://github.com/klaasnicolaas/python-parking-eindhoven
Project-URL: Repository, https://github.com/klaasnicolaas/python-parking-eindhoven
